httsleep/__init__.py
httsleep/_compat.py
httsleep/exceptions.py
httsleep/main.py
httsleep-0.3.1.dist-info/DESCRIPTION.rst
httsleep-0.3.1.dist-info/METADATA
httsleep-0.3.1.dist-info/RECORD
httsleep-0.3.1.dist-info/WHEEL
httsleep-0.3.1.dist-info/metadata.json
httsleep-0.3.1.dist-info/top_level.txt
