Metadata-Version: 2.0
Name: httsleep
Version: 0.3.1
Summary: A python library for polling HTTP endpoints - batteries included!
Home-page: https://github.com/kopf/httsleep
Author: Aengus Walton
Author-email: ventolin@gmail.com
License: Apache
Platform: UNKNOWN
Classifier: Development Status :: 4 - Beta
Classifier: License :: OSI Approved :: Apache Software License
Classifier: Programming Language :: Python
Classifier: Programming Language :: Python :: 2.7
Classifier: Programming Language :: Python :: 3.4
Classifier: Programming Language :: Python :: 3.5
Classifier: Programming Language :: Python :: 3.6
Classifier: Programming Language :: Python :: 3.7
Requires-Dist: jsonpath-rw
Requires-Dist: requests
